cirq/__init__.py
cirq/_compat.py
cirq/_compat_test.py
cirq/_doc.py
cirq/_import.py
cirq/_version.py
cirq/conftest.py
cirq/py.typed
cirq/type_workarounds.py
cirq/aqt/__init__.py
cirq/aqt/aqt_device.py
cirq/aqt/aqt_sampler.py
cirq/aqt/aqt_sampler_test.py
cirq/aqt/aqt_simulator_test.py
cirq/circuits/__init__.py
cirq/circuits/_block_diagram_drawer.py
cirq/circuits/_block_diagram_drawer_test.py
cirq/circuits/_box_drawing_character_data.py
cirq/circuits/_box_drawing_character_data_test.py
cirq/circuits/_bucket_priority_queue.py
cirq/circuits/_bucket_priority_queue_test.py
cirq/circuits/circuit.py
cirq/circuits/circuit_dag.py
cirq/circuits/circuit_dag_test.py
cirq/circuits/circuit_test.py
cirq/circuits/frozen_circuit.py
cirq/circuits/frozen_circuit_test.py
cirq/circuits/insert_strategy.py
cirq/circuits/insert_strategy_test.py
cirq/circuits/optimization_pass.py
cirq/circuits/optimization_pass_test.py
cirq/circuits/qasm_output.py
cirq/circuits/qasm_output_test.py
cirq/circuits/quil_output.py
cirq/circuits/quil_output_test.py
cirq/circuits/text_diagram_drawer.py
cirq/circuits/text_diagram_drawer_test.py
cirq/contrib/__init__.py
cirq/contrib/json.py
cirq/contrib/json_test.py
cirq/contrib/acquaintance/__init__.py
cirq/contrib/acquaintance/bipartite.py
cirq/contrib/acquaintance/bipartite_test.py
cirq/contrib/acquaintance/devices.py
cirq/contrib/acquaintance/devices_test.py
cirq/contrib/acquaintance/executor.py
cirq/contrib/acquaintance/executor_test.py
cirq/contrib/acquaintance/gates.py
cirq/contrib/acquaintance/gates_test.py
cirq/contrib/acquaintance/inspection_utils.py
cirq/contrib/acquaintance/inspection_utils_test.py
cirq/contrib/acquaintance/mutation_utils.py
cirq/contrib/acquaintance/mutation_utils_test.py
cirq/contrib/acquaintance/optimizers.py
cirq/contrib/acquaintance/optimizers_test.py
cirq/contrib/acquaintance/permutation.py
cirq/contrib/acquaintance/permutation_test.py
cirq/contrib/acquaintance/shift.py
cirq/contrib/acquaintance/shift_swap_network.py
cirq_unstable-0.10.0.dev20201203005757.dist-info/LICENSE
cirq_unstable-0.10.0.dev20201203005757.dist-info/METADATA
cirq_unstable-0.10.0.dev20201203005757.dist-info/WHEEL
cirq_unstable-0.10.0.dev20201203005757.dist-info/top_level.txt
cirq_unstable-0.10.0.dev20201203005757.dist-info/RECORD
