Metadata-Version: 2.1
Name: cirq-unstable
Version: 0.10.0.dev20201203005757
Summary: A framework for creating, editing, and invoking Noisy Intermediate Scale Quantum (NISQ) circuits.
Home-page: http://github.com/quantumlib/cirq
Author: The Cirq Developers
Author-email: cirq@googlegroups.com
License: Apache 2
Platform: UNKNOWN
Requires-Python: >=3.6.0
Requires-Dist: google-api-core[grpc] (<2.0.0dev,>=1.14.0)
Requires-Dist: matplotlib (~=3.0)
Requires-Dist: networkx (~=2.4)
Requires-Dist: numpy (~=1.16)
Requires-Dist: pandas
Requires-Dist: protobuf (~=3.13.0)
Requires-Dist: requests (~=2.18)
Requires-Dist: sortedcontainers (~=2.0)
Requires-Dist: scipy
Requires-Dist: sympy
Requires-Dist: typing-extensions
Requires-Dist: dataclasses ; python_version < "3.7"
Provides-Extra: contrib
Requires-Dist: ply (>=3.4) ; extra == 'contrib'
Requires-Dist: pylatex (~=1.3.0) ; extra == 'contrib'
Requires-Dist: quimb ; extra == 'contrib'
Requires-Dist: opt-einsum ; extra == 'contrib'
Requires-Dist: autoray ; extra == 'contrib'
Requires-Dist: pyquil (~=2.21.0) ; extra == 'contrib'
Provides-Extra: dev_env
Requires-Dist: black (==20.8b1) ; extra == 'dev_env'
Requires-Dist: mypy (~=0.782.0) ; extra == 'dev_env'
Requires-Dist: pylint (~=2.6.0) ; extra == 'dev_env'
Requires-Dist: pytest (~=5.4.1) ; extra == 'dev_env'
Requires-Dist: pytest-asyncio (~=0.12.0) ; extra == 'dev_env'
Requires-Dist: pytest-cov (~=2.5.0) ; extra == 'dev_env'
Requires-Dist: pytest-benchmark (~=3.2.0) ; extra == 'dev_env'
Requires-Dist: filelock ; extra == 'dev_env'
Requires-Dist: grpcio-tools (~=1.26) ; extra == 'dev_env'
Requires-Dist: mypy-protobuf (==1.10) ; extra == 'dev_env'
Requires-Dist: twine ; extra == 'dev_env'
Requires-Dist: pyquil (~=2.21.0) ; extra == 'dev_env'
Requires-Dist: qiskit (~=0.20.0) ; extra == 'dev_env'
Requires-Dist: pypandoc ; extra == 'dev_env'
Requires-Dist: myst-parser ; extra == 'dev_env'
Requires-Dist: Sphinx (~=3.2.0) ; extra == 'dev_env'
Requires-Dist: sphinx-rtd-theme ; extra == 'dev_env'
Requires-Dist: sphinx-markdown-tables ; extra == 'dev_env'
Requires-Dist: nbsphinx ; extra == 'dev_env'
Requires-Dist: ipython ; extra == 'dev_env'
Requires-Dist: ipykernel ; extra == 'dev_env'
Requires-Dist: rstcheck (~=3.3.1) ; extra == 'dev_env'
Requires-Dist: freezegun (~=0.3.15) ; extra == 'dev_env'
Requires-Dist: ply (>=3.4) ; extra == 'dev_env'
Requires-Dist: pylatex (~=1.3.0) ; extra == 'dev_env'
Requires-Dist: quimb ; extra == 'dev_env'
Requires-Dist: opt-einsum ; extra == 'dev_env'
Requires-Dist: autoray ; extra == 'dev_env'
